{
  "children": [
    {
      "id": "backend",
      "state": "done"

    },
    {
      "id": "object_oriented",
      "state": "done"

    },
    {
      "id": "spring",
      "children": [
        {
          "id": "spring_batch",
          "state": "done"

        },
        {
          "id": "spring_cache",
          "state": "done"

        }
      ]
    },

    {
      "id": "hibernate",
      "state": "start"
    },
    {
      "id": "maven",
      "order": "11",
      "state": "done",
      "knowledge_level" : "high"
    },
    {
      "id": "gradle",
      "state": "done",
      "knowledge_level" : "low"
    },
    {
      "id": "rx_java",
      "state": "done",
      "knowledge_level" : "med"
    },
    {
      "id": "kafka",
      "order": "19"
    }
  ]
}
